HeartbeatMaker/__init__.py
HeartbeatMaker/beater.py
HeartbeatMaker-0.9.dist-info/DESCRIPTION.rst
HeartbeatMaker-0.9.dist-info/METADATA
HeartbeatMaker-0.9.dist-info/RECORD
HeartbeatMaker-0.9.dist-info/WHEEL
HeartbeatMaker-0.9.dist-info/metadata.json
HeartbeatMaker-0.9.dist-info/top_level.txt
