Metadata-Version: 2.0
Name: HeartbeatMaker
Version: 0.9
Summary: 一个简易的定时器,会将定定时配置信息保存在redis
Home-page: http://xiangyang.li/project/python-heartbeat-maker
Author: Shawn Li
Author-email: shawn@xiangyang.li
License: Apache License
Keywords: heartbeat,redis
Platform: any
Requires-Dist: redis
